autoseqml/__init__.py
autoseqml/eda/__init__.py
autoseqml/eda/csv.py
autoseqml/eda/eda.py
autoseqml/eda/txt.py
autoseqml/llm/__init__.py
autoseqml/llm/classify.py
autoseqml/llm/dataset.py
autoseqml/llm/forecast.py
autoseqml/pm/__init__.py
autoseqml/pm/encode.py
autoseqml/pm/weather.py
autoseqml/utils/__init__.py
autoseqml/utils/config.ini
autoseqml/utils/exceptions.py
eda/__init__.py
eda/csv.py
eda/txt.py
llm/__init__.py
llm/classify.py
llm/dataset.py
llm/forecast.py
pm/__init__.py
pm/encode.py
pm/weather.py
utils/__init__.py
utils/exceptions.py
autoseqml-0.1.1.dist-info/LICENSE
autoseqml-0.1.1.dist-info/METADATA
autoseqml-0.1.1.dist-info/WHEEL
autoseqml-0.1.1.dist-info/top_level.txt
autoseqml-0.1.1.dist-info/RECORD
