Metadata-Version: 2.1
Name: autoseqml
Version: 0.1.1
Summary: A tool for dealing sequential data for machine learning
Home-page: https://github.com/kurokumasan/AutoSeqML
Author: Kun-Lin, Ho
Author-email: m11015064@mail.ntust.edu.tw
License: MIT
Platform: UNKNOWN
Classifier: Programming Language :: Python :: 3.7
Classifier: Programming Language :: Python :: 3.8
Classifier: Programming Language :: Python :: 3.9
Classifier: Programming Language :: Python :: 3.10
Classifier: Programming Language :: Python :: 3.11
Requires-Python: >=3.7
Provides-Extra: dev
